Metadata-Version: 2.1
Name: zmb-distributions
Version: 0.2.5
Summary: Gaussian and binomial distributions
Home-page: UNKNOWN
License: UNKNOWN
Platform: UNKNOWN
